<layer>
  <name>tasmania_state_boundaries-copy-741</name>
  <id>LayerInfoImpl-d394fa8:190bfbfea91:-65de</id>
  <type>VECTOR</type>
  <defaultStyle>
    <id>StyleInfoImpl--2e943405:190bfb90dd9:-7ffe</id>
  </defaultStyle>
  <resource class="featureType">
    <id>FeatureTypeInfoImpl-d394fa8:190bfbfea91:-65df</id>
  </resource>
  <queryable>true</queryable>
  <opaque>false</opaque>
  <attribution>
    <logoWidth>0</logoWidth>
    <logoHeight>0</logoHeight>
  </attribution>
  <dateCreated>2024-07-17 08:26:59.822 UTC</dateCreated>
</layer>